MANIFEST.in
README
__init__.py
__pkginfo__.py
entities.py
schema.py
setup.py
site_cubicweb.py
sobjects.py
cubicweb_mandrill.egg-info/PKG-INFO
cubicweb_mandrill.egg-info/SOURCES.txt
cubicweb_mandrill.egg-info/dependency_links.txt
cubicweb_mandrill.egg-info/not-zip-safe
cubicweb_mandrill.egg-info/requires.txt
cubicweb_mandrill.egg-info/top_level.txt
test/test_mandrill.py
test/test_notif.py
testdata/__init__.py