Metadata-Version: 1.1
Name: cubicweb-mandrill
Version: 0.3.0
Summary: Mandrill Integration cube
Home-page: http://www.cubicweb.org/project/cubicweb-mandrill
Author: UNLISH (Montpellier, France)
Author-email: contact@unlish.com
License: LGPL
Platform: UNKNOWN
Classifier: Environment :: Web Environment
Classifier: Framework :: CubicWeb
Classifier: Programming Language :: Python
Classifier: Programming Language :: JavaScript
